{"content": ["All legislative powers of the city shall be vested in a council consisting of five (5) councilmembers who shall be elected as hereinafter provided and who shall hold office for a term of four (4) years or until their successors shall take office. The regular term of each councilmember shall expire on the first Monday following the election of his successor. Subject to the provisions of section 31 of this Charter, two (2) councilmembers shall be elected in 1986, then in 1989 and in every fourth year thereafter and three (3) councilmembers shall be elected in 1988, then in 1991 and in every fourth year thereafter."], "note": null, "history": "(Ord. No. CA-1-74, \u00a7 1; Res. No. CA-1-86, 1-21-86)", "number": "3", "title": "Council-Legislative authority of city; number of councilmembers; term of office of councilmembers."}